{
"type": "FeatureCollection",
"name": "948840c1f52f4a4690a96fe3c5ada1df",
"crs": { "type": "name", "properties": { "name": "urn:ogc:def:crs:OGC:1.3:CRS84" } },
"xy_coordinate_resolution": 1e-07,
"features": [
{ "type": "Feature", "properties": { "time": "2010-09-10T00:00:00", "temperature": 13.345, "pressure": 1.9003, "temperature_std": 0.10118, "pressure_std": 3.9826 }, "geometry": { "type": "Point", "coordinates": [ -5.15625, 48.5322537 ] } },
{ "type": "Feature", "properties": { "time": "2010-09-11T00:00:00", "temperature": 13.542, "pressure": 0.99313, "temperature_std": 0.081261, "pressure_std": 0.79748 }, "geometry": { "type": "Point", "coordinates": [ -5.0763359, 48.7153824 ] } },
{ "type": "Feature", "properties": { "time": "2010-09-12T00:00:00", "temperature": 13.811, "pressure": 1.5091, "temperature_std": 0.2036, "pressure_std": 1.9014 }, "geometry": { "type": "Point", "coordinates": [ -5.0184136, 48.8008048 ] } },
{ "type": "Feature", "properties": { "time": "2010-09-13T00:00:00", "temperature": 13.945, "pressure": 1.6013, "temperature_std": 0.067346, "pressure_std": 1.7154 }, "geometry": { "type": "Point", "coordinates": [ -5.0369004, 48.8862032 ] } },
{ "type": "Feature", "properties": { "time": "2010-09-14T00:00:00", "temperature": 14.511, "pressure": 1.0068, "temperature_std": 0.2141, "pressure_std": 0.82195 }, "geometry": { "type": "Point", "coordinates": [ -5.3078888, 48.8740048 ] } },
{ "type": "Feature", "properties": { "time": "2010-09-15T00:00:00", "temperature": 15.381, "pressure": 1.0378, "temperature_std": 0.38159, "pressure_std": 0.91417 }, "geometry": { "type": "Point", "coordinates": [ -5.4456429, 48.8862032 ] } },
{ "type": "Feature", "properties": { "time": "2010-09-16T00:00:00", "temperature": 16.512, "pressure": 1.1962, "temperature_std": 0.48136, "pressure_std": 1.9912 }, "geometry": { "type": "Point", "coordinates": [ -5.6191423, 48.9105983 ] } },
{ "type": "Feature", "properties": { "time": "2010-09-17T00:00:00", "temperature": 17.336, "pressure": 1.738, "temperature_std": 0.15065, "pressure_std": 3.8631 }, "geometry": { "type": "Point", "coordinates": [ -5.7829787, 48.8618061 ] } },
{ "type": "Feature", "properties": { "time": "2010-09-18T00:00:00", "temperature": 17.345, "pressure": 2.2959, "temperature_std": 0.26247, "pressure_std": 5.7719 }, "geometry": { "type": "Point", "coordinates": [ -5.9872521, 48.8008048 ] } },
{ "type": "Feature", "properties": { "time": "2010-09-19T00:00:00", "temperature": 17.436, "pressure": 3.074, "temperature_std": 0.17689, "pressure_std": 2.9245 }, "geometry": { "type": "Point", "coordinates": [ -6.0433182, 48.7764008 ] } },
{ "type": "Feature", "properties": { "time": "2010-09-20T00:00:00", "temperature": 17.454, "pressure": 4.7522, "temperature_std": 0.072283, "pressure_std": 5.6562 }, "geometry": { "type": "Point", "coordinates": [ -6.2108383, 48.6421442 ] } },
{ "type": "Feature", "properties": { "time": "2010-09-21T00:00:00", "temperature": 17.476, "pressure": 2.7333, "temperature_std": 0.16032, "pressure_std": 3.9464 }, "geometry": { "type": "Point", "coordinates": [ -6.2207499, 48.5933089 ] } },
{ "type": "Feature", "properties": { "time": "2010-09-22T00:00:00", "temperature": 17.544, "pressure": 1.786, "temperature_std": 0.12957, "pressure_std": 3.3719 }, "geometry": { "type": "Point", "coordinates": [ -6.1953764, 48.5933089 ] } },
{ "type": "Feature", "properties": { "time": "2010-09-23T00:00:00", "temperature": 17.459, "pressure": 2.2531, "temperature_std": 0.041559, "pressure_std": 4.3229 }, "geometry": { "type": "Point", "coordinates": [ -6.180203, 48.6055185 ] } },
{ "type": "Feature", "properties": { "time": "2010-09-24T00:00:00", "temperature": 17.218, "pressure": 0.56466, "temperature_std": 0.20352, "pressure_std": 0.79598 }, "geometry": { "type": "Point", "coordinates": [ -6.2105411, 48.5810989 ] } }
]
}
